LICENSE.txt
setup.py
codigofacilito_DaryCC/__init__.py
codigofacilito_DaryCC/__main__.py
codigofacilito_DaryCC/config.py
codigofacilito_DaryCC/workshops.py
codigofacilito_DaryCC.egg-info/PKG-INFO
codigofacilito_DaryCC.egg-info/SOURCES.txt
codigofacilito_DaryCC.egg-info/dependency_links.txt
codigofacilito_DaryCC.egg-info/requires.txt
codigofacilito_DaryCC.egg-info/top_level.txt