Metadata-Version: 2.1
Name: codigofacilito-DaryCC
Version: 0.0.1
Summary: Consumir el API de CodigoFacilito
Home-page: https://github.com/DaryCC/codigofacilito_package
Author: Daryberto Canseco Cortés
Author-email: dary.cc@gmail.com
License: MIT
Keywords: daryberto,codigo facilito,código facilito,codigofacilito
Platform: UNKNOWN
Classifier: Development Status :: 3 - Alpha
Classifier: Intended Audience :: Developers
Classifier: Topic :: Software Development :: Build Tools
Classifier: License :: OSI Approved :: MIT License
Classifier: Programming Language :: Python :: 3
License-File: LICENSE.txt
